jxcrawl/__init__.py
jxcrawl/common_config.py
jxcrawl/jxcrawl_lib.py
jxcrawl/readme.txt
jxcrawl-3.0.dist-info/METADATA
jxcrawl-3.0.dist-info/WHEEL
jxcrawl-3.0.dist-info/top_level.txt
jxcrawl-3.0.dist-info/RECORD
